docsteady/__init__.py
docsteady/config.py
docsteady/cycle.py
docsteady/formatters.py
docsteady/spec.py
docsteady/tplan.py
docsteady/utils.py
docsteady/vcd.py
docsteady/ve_baseline.py
docsteady/templates/dm-cycle.html.jinja2
docsteady/templates/dm-cycle.latex.jinja2
docsteady/templates/example-spec.markdown.jinja2
docsteady/templates/se-tpr.latex.jinja2
docsteady/templates/spec-appendix.latex.jinja2
docsteady/templates/spec.latex.jinja2
docsteady/templates/tpnoresult.latex.jinja2
docsteady/templates/tpr-appendix.latex.jinja2
docsteady/templates/tpr.latex.jinja2
docsteady/templates/ts-tpr.latex.jinja2
docsteady/templates/vcd.latex.jinja2
docsteady/templates/ve-details.latex.jinja2
docsteady/templates/ve.latex.jinja2
docsteady-3.1.4.dist-info/licenses/LICENSE
docsteady-3.1.4.dist-info/METADATA
docsteady-3.1.4.dist-info/WHEEL
docsteady-3.1.4.dist-info/entry_points.txt
docsteady-3.1.4.dist-info/top_level.txt
docsteady-3.1.4.dist-info/RECORD
