Metadata-Version: 2.4
Name: docsteady
Version: 3.1.4
Summary: Generate test relted documentation from Zephyrscale Jira Test
License:                     GNU GENERAL PUBLIC LICENSE
Project-URL: Homepage, https://docsteady.lsst.io
Project-URL: Source, https://github.com/lsst-dm/docsteady
Keywords: rubin,lsst
Classifier: Development Status :: 4 - Beta
Classifier: License :: OSI Approved :: MIT License
Classifier: Programming Language :: Python
Classifier: Programming Language :: Python :: 3
Classifier: Programming Language :: Python :: 3.13
Classifier: Intended Audience :: Developers
Classifier: Natural Language :: English
Classifier: Operating System :: POSIX
Requires-Python: >=3.11
License-File: LICENSE
Requires-Dist: idna>=3.7
Requires-Dist: certifi>2024.2.0
Requires-Dist: pillow>=10.3.0
Requires-Dist: ecdsa>=0.18
Requires-Dist: BeautifulSoup4
Requires-Dist: click
Requires-Dist: jinja2>=3.1.5
Requires-Dist: marshmallow<4.0
Requires-Dist: pandoc
Requires-Dist: pypandoc
Requires-Dist: pydantic
Requires-Dist: requests>2.32.0
Requires-Dist: arrow
Requires-Dist: urllib3>=2.2.2
Requires-Dist: tlslite-ng
Requires-Dist: oauth2
Requires-Dist: zephyr-python-api
Provides-Extra: dev
Requires-Dist: pre-commit>=4.0.1; extra == "dev"
Requires-Dist: pytest; extra == "dev"
Requires-Dist: pytest-cov; extra == "dev"
Requires-Dist: mypy; extra == "dev"
Requires-Dist: types-requests; extra == "dev"
Requires-Dist: documenteer>1.0.0; extra == "dev"
Requires-Dist: documenteer[guide]; extra == "dev"
Requires-Dist: sphinx-rtd-theme; extra == "dev"
Requires-Dist: sphinx-prompt; extra == "dev"
Dynamic: license-file
